vertibench/Evaluator.py
vertibench/Splitter.py
vertibench/__init__.py
vertibench-0.1.1.dist-info/LICENSE
vertibench-0.1.1.dist-info/METADATA
vertibench-0.1.1.dist-info/WHEEL
vertibench-0.1.1.dist-info/top_level.txt
vertibench-0.1.1.dist-info/RECORD
