Metadata-Version: 2.1
Name: vertibench
Version: 0.1.1
Summary: A tool for benchmarking vertical federated learning algorithms, containing synthetic data split and data evaluation.
Author: Junyi Hou, Bingsheng He
Author-email: Zhaomin Wu <hustwuzhaomin@outlook.com>
License: Apache License
Project-URL: Homepage, https://github.com/Xtra-Computing/VertiBench
Keywords: vertical federated learning,benchmark,synthetic data,feature split,data valuation,federated learning
Classifier: Development Status :: 3 - Alpha
Classifier: Intended Audience :: Developers
Classifier: License :: OSI Approved :: Apache Software License
Classifier: Programming Language :: Python :: 3
Classifier: Programming Language :: Python :: 3.10
License-File: LICENSE
Requires-Dist: matplotlib >=3.7
Requires-Dist: numpy ==1.24
Requires-Dist: pymoo ==0.6.1.1
Requires-Dist: scikit-learn >=1.2
Requires-Dist: scipy >=1.10
Requires-Dist: shap ==0.43
Requires-Dist: torch >=2.0
Provides-Extra: test
Requires-Dist: xgboost >=2.0 ; extra == 'test'
